{
    "ajax_request": "คำขอ Ajax",
    "archive_create_error": "ไม่สามารถสร้างที่เก็บถาวร",
    "archive_create_success": "เก็บถาวรสร้างสำเร็จแล้ว",
    "archive_invalid_format": "ระบุรูปแบบการเก็บถาวรไม่ถูกต้อง",
    "archivename": "ชื่อของที่เก็บถาวร",
    "cancel": "ยกเลิก",
    "close": "ปิด",
    "copy_error": "ไม่สามารถคัดลอกไฟล์ต่อไปนี้:",
    "copy_success": "คัดลอกไฟล์สำเร็จแล้ว",
    "copy": "สำเนา",
    "copylink": "คัดลอกลิงค์",
    "create_archive": "สร้างที่เก็บถาวร",
    "data": "ข้อมูล",
    "delete": "ลบ",
    "dimensions": "มิติ",
    "directoryname": "ชื่อไดเรกทอรี",
    "download": "ดาวน์โหลด",
    "edit": "แก้ไข",
    "editor_options": "ตัวเลือกบรรณาธิการ",
    "error": "ข้อผิดพลาด:",
    "extract_error": "ไม่สามารถแยกไฟล์เก็บถาวร",
    "extract_filename": "ไฟล์แยก -",
    "extract_success": "เก็บถาวรสกัดสำเร็จแล้ว",
    "extract": "สารสกัด",
    "file_copy_to": "ถึง",
    "file_delete_confirm": "คุณต้องการลบไฟล์ต่อไปนี้จริงๆ -",
    "file_delete_error": "ไม่สามารถลบไฟล์ได้",
    "file_delete_success": "ลบไฟล์สำเร็จแล้ว",
    "file_display_error": "ไฟล์นี้ไม่สามารถแสดงหรือแก้ไขได้",
    "file_load_error": "ไม่สามารถโหลดเนื้อหาได้",
    "file_new": "ไฟล์ใหม่",
    "file_no_permission": "ไม่อนุญาตให้แก้ไข / สร้างไฟล์",
    "file_not_found": "ไม่พบไฟล์หรือไม่สามารถเปิดได้",
    "file_open_error": "ไม่สามารถเปิดไฟล์ได้",
    "file_overwrite": "เขียนทับไฟล์ที่มีอยู่",
    "file_rename_error": "ไม่สามารถเปลี่ยนชื่อไฟล์ได้:",
    "file_rename_success": "ไฟล์เปลี่ยนชื่อเรียบร้อยแล้ว",
    "file_rename": "เปลี่ยนชื่อไฟล์",
    "file_save_confirm": "คุณต้องการบันทึกไฟล์ต่อไปนี้ -",
    "file_save_error": "ไม่สามารถบันทึกไฟล์ได้",
    "file_save_success": "บันทึกไฟล์สำเร็จแล้ว",
    "file_upload_error": "ไม่สามารถอัปโหลดไฟล์ได้",
    "file_upload_success": "อัปโหลดไฟล์สำเร็จแล้ว",
    "filename_new": "ชื่อไฟล์ใหม่",
    "filename_slashes": "ชื่อไฟล์จะต้องไม่มีเครื่องหมายสแลช",
    "filename": "ชื่อไฟล์",
    "filter": "กรอง",
    "folder_create_error": "ไม่สามารถสร้างไดเรกทอรีได้",
    "folder_create_success": "ไดเรกทอรีที่สร้างขึ้นอย่างสำเร็จ",
    "folder_new": "แฟ้มใหม่",
    "folder_not_found": "ไม่พบไดเรกทอรี",
    "folder_tree_load_error": "เกิดข้อผิดพลาดขณะดึงแผนผังโฟลเดอร์",
    "footer": "IFM - ปรับปรุงตัวจัดการไฟล์ | ifm.php ซ่อน",
    "general_error": "เกิดข้อผิดพลาดทั่วไป: ไม่ตอบสนองหรือหัก",
    "github": "เยี่ยมชมโครงการใน GitHub",
    "group": "กลุ่ม",
    "height": "ส่วนสูง",
    "invalid_action": "การกระทำที่ไม่ถูกต้อง",
    "invalid_archive_format": "ระบุรูปแบบการเก็บถาวรไม่ถูกต้อง รูปแบบที่เป็นไปได้คือ zip, tar, tar.gz หรือ tar.bz2",
    "invalid_data": "ข้อมูลไม่ถูกต้องจากเซิร์ฟเวอร์",
    "invalid_dir": "กำหนดไดเรกทอรีไม่ถูกต้อง",
    "invalid_filename": "ชื่อไฟล์ที่ไม่ถูกต้อง",
    "invalid_params": "พารามิเตอร์ที่ไม่ถูกต้องให้",
    "invalid_url": "URL ที่ไม่ถูกต้องให้",
    "json_encode_error": "ไม่สามารถฟอร์แมตการตอบสนองเป็น JSON:",
    "last_modified": "แก้ไขล่าสุด",
    "load_config_error": "ไม่สามารถโหลดการกำหนดค่า",
    "load_template_error": "ไม่สามารถโหลดเทมเพลต",
    "load_text_error": "ไม่สามารถโหลดข้อความได้",
    "login_failed": "การเข้าสู่ระบบล้มเหลว",
    "login": "เข้าสู่ระบบ",
    "logout": "ออกจากระบบ",
    "method": "วิธี",
    "move_error": "ไม่สามารถย้ายไฟล์ต่อไปนี้:",
    "move_success": "ย้ายไฟล์สำเร็จแล้ว",
    "move": "เคลื่อนไหว",
    "nopermissions": "คุณไม่มีสิทธิ์ในการทำเช่นนั้น",
    "options": "ตัวเลือก",
    "owner": "เจ้าของ",
    "password": "รหัสผ่าน",
    "path_content": "เนื้อหาของ",
    "pattern_error_slashes": "รูปแบบต้องไม่มีเครื่องหมายสแลช",
    "permission_change_error": "การอนุญาตไม่สามารถเปลี่ยนแปลงได้:",
    "permission_change_success": "การอนุญาตเปลี่ยนการอนุญาตสำเร็จแล้ว",
    "permission_parse_error": "สิทธิ์ไม่สามารถแยกวิเคราะห์ได้อย่างถูกต้อง",
    "permissions": "การอนุญาต",
    "refresh": "รีเฟรช",
    "remaining_tasks": "มีภารกิจที่เหลืออยู่ คุณต้องการโหลดซ้ำจริงๆหรือ",
    "rename_filename": "เปลี่ยนชื่อไฟล์ -",
    "rename": "การเปลี่ยนชื่อ",
    "request": "ขอ",
    "response": "การตอบสนอง",
    "save_wo_close": "บันทึก w / o close",
    "save": "บันทึก",
    "search_pattern": "รูปแบบ",
    "search": "ค้นหา",
    "select_destination": "เลือกปลายทาง",
    "size": "ขนาด",
    "soft_tabs": "แท็บนุ่ม",
    "tab_size": "ขนาดแท็บ",
    "tasks": "ภารกิจ",
    "thumbs_directoryname": "ชื่อไดเรกทอรีสำหรับรูปขนาดย่อ",
    "thumbs_folder_new": "สร้างโฟลเดอร์ขนาดย่อ",
    "thumbs_square": "สร้างภาพขนาดย่อของสแควร์",
    "toggle_nav": "ไม่ต้องสลับช่องทาง",
    "upload_drop": "วางไฟล์ที่จะอัปโหลด",
    "upload_file": "อัพโหลดไฟล์",
    "upload_overwrite_confirm": "อัปโหลดต่อไป?",
    "upload_overwrite_hint": "ไฟล์ต่อไปนี้จะถูกเขียนทับ:",
    "upload_remote_url": "URL อัพโหลดระยะไกล",
    "upload_remote": "อัพโหลดระยะไกล",
    "upload": "ที่อัพโหลด",
    "username": "ชื่อผู้ใช้",
    "width": "ความกว้าง",
    "word_wrap": "ตัดคำ"
}